fBms/__init__.py
fBms/core.py
fBms-0.2.0.dist-info/LICENSE
fBms-0.2.0.dist-info/METADATA
fBms-0.2.0.dist-info/WHEEL
fBms-0.2.0.dist-info/top_level.txt
fBms-0.2.0.dist-info/RECORD
