Metadata-Version: 2.1
Name: fBms
Version: 0.2.0
Summary: fBms python package
Home-page: https://github.com/antoinemarchal/fBms
Author: Antoine Marchal
Author-email: amarchal@cita.utoronto.ca
License: THE WORK (AS DEFINED BELOW) IS PROVIDED UNDER THE TERMS OF THIS CREATIVE COMMONS PUBLIC LICENSE ("CCPL" OR "LICENSE"). THE WORK IS PROTECTED BY COPYRIGHT AND/OR OTHER APPLICABLE LAW. ANY USE OF THE WORK OTHER THAN AS AUTHORIZED UNDER THIS LICENSE OR COPYRIGHT LAW IS PROHIBITED.
Requires-Dist: numpy
Requires-Dist: six
